pytest_replay/__init__.py
pytest_replay-1.7.1.dist-info/licenses/LICENSE
pytest_replay-1.7.1.dist-info/METADATA
pytest_replay-1.7.1.dist-info/WHEEL
pytest_replay-1.7.1.dist-info/entry_points.txt
pytest_replay-1.7.1.dist-info/top_level.txt
pytest_replay-1.7.1.dist-info/RECORD
